pyntegritydb/__init__.py
pyntegritydb/alerts.py
pyntegritydb/cli.py
pyntegritydb/config.py
pyntegritydb/connect.py
pyntegritydb/metrics.py
pyntegritydb/report.py
pyntegritydb/schema.py
pyntegritydb/visualize.py
pyntegritydb-0.3.0.dist-info/licenses/LICENSE
pyntegritydb-0.3.0.dist-info/METADATA
pyntegritydb-0.3.0.dist-info/WHEEL
pyntegritydb-0.3.0.dist-info/entry_points.txt
pyntegritydb-0.3.0.dist-info/top_level.txt
pyntegritydb-0.3.0.dist-info/RECORD
