Metadata-Version: 2.4
Name: pyntegritydb
Version: 0.3.0
Summary: Una biblioteca para medir la calidad de la integridad referencial en bases de datos relacionales.
Author-email: Osvaldo Trujillo <osvaldo.trujillo.ingenieria@gmail.com>
License: MIT License
Project-URL: Homepage, https://github.com/osvaldomx/pyntegritydb
Project-URL: Repository, https://github.com/osvaldomx/pyntegritydb
Project-URL: Changelog, https://github.com/osvaldomx/pyntegritydb/releases/tag/v0.2.0
Project-URL: Issues, https://github.com/osvaldomx/pyntegritydb/issues
Keywords: database,integrity,data quality,sql,validator
Classifier: Development Status :: 4 - Beta
Classifier: Intended Audience :: Developers
Classifier: Intended Audience :: System Administrators
Classifier: Topic :: Database
Classifier: Topic :: Software Development :: Quality Assurance
Classifier: Topic :: Software Development :: Libraries :: Python Modules
Classifier: License :: OSI Approved :: MIT License
Classifier: Programming Language :: Python :: 3.12
Classifier: Operating System :: OS Independent
Requires-Python: >=3.12
License-File: LICENSE
Requires-Dist: psycopg2-binary==2.9.10
Requires-Dist: sqlalchemy>=2.0
Requires-Dist: networkx>=3.0
Requires-Dist: pandas>=2.0
Requires-Dist: tabulate>=0.9
Requires-Dist: PyYAML>=6.0
Requires-Dist: matplotlib>=3.7
Provides-Extra: dev
Requires-Dist: pytest==8.4.1; extra == "dev"
Requires-Dist: mock==5.2.0; extra == "dev"
Requires-Dist: PyYAML>=6.0; extra == "dev"
Requires-Dist: pytest-cov; extra == "dev"
Requires-Dist: ruff; extra == "dev"
Provides-Extra: docs
Requires-Dist: sphinx; extra == "docs"
Requires-Dist: sphinx-rtd-theme; extra == "docs"
Dynamic: license-file
